odoo/addons/website_sale_loyalty_page/README.rst
odoo/addons/website_sale_loyalty_page/__init__.py
odoo/addons/website_sale_loyalty_page/__manifest__.py
odoo/addons/website_sale_loyalty_page/controllers/__init__.py
odoo/addons/website_sale_loyalty_page/controllers/main.py
odoo/addons/website_sale_loyalty_page/i18n/es.po
odoo/addons/website_sale_loyalty_page/i18n/it.po
odoo/addons/website_sale_loyalty_page/i18n/website_sale_loyalty_page.pot
odoo/addons/website_sale_loyalty_page/models/__init__.py
odoo/addons/website_sale_loyalty_page/models/loyalty_program.py
odoo/addons/website_sale_loyalty_page/readme/CONFIGURE.md
odoo/addons/website_sale_loyalty_page/readme/CONTRIBUTORS.md
odoo/addons/website_sale_loyalty_page/readme/DESCRIPTION.md
odoo/addons/website_sale_loyalty_page/readme/USAGE.md
odoo/addons/website_sale_loyalty_page/static/description/icon.png
odoo/addons/website_sale_loyalty_page/static/description/index.html
odoo/addons/website_sale_loyalty_page/static/src/scss/styles.scss
odoo/addons/website_sale_loyalty_page/static/tests/tours/website_sale_loyalty_page_portal.esm.js
odoo/addons/website_sale_loyalty_page/templates/promotion_templates.xml
odoo/addons/website_sale_loyalty_page/tests/__init__.py
odoo/addons/website_sale_loyalty_page/tests/test_website_sale_loyalty_page.py
odoo/addons/website_sale_loyalty_page/views/sale_loyalty_program_views.xml
odoo_addon_website_sale_loyalty_page-18.0.1.0.0.2.dist-info/METADATA
odoo_addon_website_sale_loyalty_page-18.0.1.0.0.2.dist-info/WHEEL
odoo_addon_website_sale_loyalty_page-18.0.1.0.0.2.dist-info/top_level.txt
odoo_addon_website_sale_loyalty_page-18.0.1.0.0.2.dist-info/RECORD
